llmdatalens/__init__.py
llmdatalens/core/__init__.py
llmdatalens/core/base_model.py
llmdatalens/core/enums.py
llmdatalens/core/metrics.py
llmdatalens/core/metrics_registry.py
llmdatalens/evaluators/__init__.py
llmdatalens/evaluators/field_evaluators.py
llmdatalens/evaluators/llm_evaluator.py
llmdatalens/evaluators/structured_output_evaluator.py
llmdatalens/experiment/__init__.py
llmdatalens/experiment/experiment_manager.py
llmdatalens/experiment/models.py
llmdatalens/utils/__init__.py
llmdatalens/visualization/__init__.py
llm_data_lens-0.1.5.dist-info/LICENSE.txt
llm_data_lens-0.1.5.dist-info/METADATA
llm_data_lens-0.1.5.dist-info/WHEEL
llm_data_lens-0.1.5.dist-info/RECORD
